izulu/__init__.py
izulu/_reraise.py
izulu/_utils.py
izulu/py.typed
izulu/root.py
izulu/tools.py
izulu-0.70.0.dist-info/licenses/LICENSE
izulu-0.70.0.dist-info/METADATA
izulu-0.70.0.dist-info/WHEEL
izulu-0.70.0.dist-info/top_level.txt
izulu-0.70.0.dist-info/RECORD
