Metadata-Version: 2.4
Name: izulu
Version: 0.70.0
Summary: The exceptional library
Author-email: Dima Burmistrov <pyctrl.dev@gmail.com>
Project-URL: homepage, https://github.com/pyctrl/izulu
Project-URL: source, https://github.com/pyctrl/izulu
Project-URL: documentation, https://izulu.readthedocs.io/en/latest/
Project-URL: issues, https://github.com/pyctrl/izulu/issues
Keywords: error,exception,oop,izulu
Classifier: Programming Language :: Python :: 3
Classifier: License :: OSI Approved :: MIT License
Classifier: Operating System :: OS Independent
Classifier: Development Status :: 4 - Beta
Classifier: Intended Audience :: Developers
Classifier: Topic :: Software Development :: Libraries
Classifier: Topic :: Software Development :: Libraries :: Python Modules
Classifier: Typing :: Typed
Requires-Python: >=3.9
License-File: LICENSE
Provides-Extra: compatibility
Requires-Dist: typing-extensions>=4.5.0; extra == "compatibility"
Dynamic: license-file
